aihelper_akshay1/__init__.py
aihelper_akshay1/client.py
aihelper_akshay1/utils.py
gemini_botyy-0.2.2.dist-info/licenses/LICENSE
gemini_botyy-0.2.2.dist-info/METADATA
gemini_botyy-0.2.2.dist-info/WHEEL
gemini_botyy-0.2.2.dist-info/top_level.txt
gemini_botyy-0.2.2.dist-info/RECORD
