Metadata-Version: 2.4
Name: gemini-botyy
Version: 0.2.2
Summary: A helper library for AI text generation using Google Gemini API.
Author-email: Akshay Shibu <example@gmail.com>
License: MIT
Project-URL: Homepage, https://github.com/yourusername/aihelper_akshay1
Requires-Python: >=3.8
License-File: LICENSE
Requires-Dist: google-genai>=0.1.0
Dynamic: license-file
